timrr.py
timrr-1.0.1.dist-info/LICENSE
timrr-1.0.1.dist-info/WHEEL
timrr-1.0.1.dist-info/METADATA
timrr-1.0.1.dist-info/RECORD
