Metadata-Version: 2.1
Name: timrr
Version: 1.0.1
Summary: Time to submit while mobile working
License: GPL-3.0-or-later
Author: MikeGlotzkowski
Author-email: sebastian.lischewski@outlook.com
Requires-Python: >=3.8,<4.0
Classifier: License :: OSI Approved :: GNU General Public License v3 or later (GPLv3+)
Classifier: Programming Language :: Python :: 3
Classifier: Programming Language :: Python :: 3.8
Classifier: Programming Language :: Python :: 3.9
Requires-Dist: click (>=7.1.2,<8.0.0)
Requires-Dist: tabulate (>=0.8.9,<0.9.0)
